fpylll/util.cpython-310-x86_64-linux-gnu.so
fpylll/config.cpython-310-x86_64-linux-gnu.so
fpylll/__init__.py
fpylll/io.cpython-310-x86_64-linux-gnu.so
fpylll/fplll/bkz_param.cpython-310-x86_64-linux-gnu.so
fpylll/fplll/integer_matrix.cpython-310-x86_64-linux-gnu.so
fpylll/fplll/svpcvp.cpython-310-x86_64-linux-gnu.so
fpylll/fplll/__init__.py
fpylll/fplll/gso.cpython-310-x86_64-linux-gnu.so
fpylll/fplll/pruner.cpython-310-x86_64-linux-gnu.so
fpylll/fplll/wrapper.cpython-310-x86_64-linux-gnu.so
fpylll/fplll/lll.cpython-310-x86_64-linux-gnu.so
fpylll/fplll/bkz.cpython-310-x86_64-linux-gnu.so
fpylll/fplll/enumeration.cpython-310-x86_64-linux-gnu.so
fpylll/tools/compare.py
fpylll/tools/__init__.py
fpylll/tools/bkz_stats.py
fpylll/tools/quality.py
fpylll/tools/bkz_plot.py
fpylll/tools/bkz_simulator.py
fpylll/tools/benchmark.py
fpylll/gmp/pylong.cpython-310-x86_64-linux-gnu.so
fpylll/gmp/__init__.py
fpylll/algorithms/simple_bkz.py
fpylll/algorithms/bkz.py
fpylll/algorithms/simple_dbkz.py
fpylll/algorithms/__init__.py
fpylll/algorithms/bkz2.py
fpylll/algorithms/babai.py
fpylll-0.6.3.dist-info/METADATA
fpylll-0.6.3.dist-info/RECORD
fpylll-0.6.3.dist-info/top_level.txt
fpylll-0.6.3.dist-info/WHEEL
fpylll-0.6.3.dist-info/LICENSE
fpylll.libs/libgcc_s-a3a07607.so.1
fpylll.libs/libgmp-f5d74d1d.so.10.5.0
fpylll.libs/libmpfr-73d44616.so.6.2.1
fpylll.libs/libstdc++-496613c0.so.6.0.32
fpylll.libs/libfplll-fdfbfcb9.so.9.0.0
