Metadata-Version: 2.1
Name: fpylll
Version: 0.6.3
Summary: A Python interface for https://github.com/fplll/fplll
Home-page: https://github.com/fplll/fpylll
Author: Martin R. Albrecht
Author-email: fplll-devel@googlegroups.com
License: GNU General Public License, version 2 or later
License-File: LICENSE
